collective.clamav-3.0.0-py3.7-nspkg.pth
collective/clamav/__init__.py
collective/clamav/configure.zcml
collective/clamav/interfaces.py
collective/clamav/scanner.py
collective/clamav/setuphandlers.py
collective/clamav/testing.py
collective/clamav/validator.py
collective/clamav/browser/__init__.py
collective/clamav/browser/configure.zcml
collective/clamav/browser/controlpanel.py
collective/clamav/browser/overrides/.gitkeep
collective/clamav/browser/static/.gitkeep
collective/clamav/locales/collective.clamav.pot
collective/clamav/locales/update.sh
collective/clamav/profiles/default/browserlayer.xml
collective/clamav/profiles/default/controlpanel.xml
collective/clamav/profiles/default/metadata.xml
collective/clamav/profiles/default/propertiestool.xml
collective/clamav/profiles/default/registry.xml
collective/clamav/profiles/uninstall/browserlayer.xml
collective/clamav/tests/__init__.py
collective/clamav/tests/test_functional.py
collective/clamav/tests/test_scanner.py
collective/clamav/tests/test_setup.py
collective/clamav/tests/data/image.png
collective.clamav-3.0.0.dist-info/METADATA
collective.clamav-3.0.0.dist-info/WHEEL
collective.clamav-3.0.0.dist-info/entry_points.txt
collective.clamav-3.0.0.dist-info/namespace_packages.txt
collective.clamav-3.0.0.dist-info/top_level.txt
collective.clamav-3.0.0.dist-info/RECORD
